supersetapiclient/__init__.py
supersetapiclient/assets.py
supersetapiclient/base.py
supersetapiclient/charts.py
supersetapiclient/client.py
supersetapiclient/css_templates.py
supersetapiclient/dashboards.py
supersetapiclient/databases.py
supersetapiclient/datasets.py
supersetapiclient/exceptions.py
supersetapiclient/saved_queries.py
superset_python_client-1.1.3.dist-info/LICENSE
superset_python_client-1.1.3.dist-info/METADATA
superset_python_client-1.1.3.dist-info/WHEEL
superset_python_client-1.1.3.dist-info/RECORD
