Metadata-Version: 2.1
Name: superset-python-client
Version: 1.1.3
Summary: A simple REST API Client for Apache-Superset in Python
Home-page: https://github.com/ishahroz/superset-python-client
License: MIT
Author: Shahroz Ahmad
Author-email: ishahrozahmad90@gmail.com
Requires-Python: >=3.12,<3.13
Classifier: License :: OSI Approved :: MIT License
Classifier: Programming Language :: Python :: 3
Classifier: Programming Language :: Python :: 3.12
Requires-Dist: cached-property (>=1.5.2,<2.0.0)
Requires-Dist: pyjwt (>=2.9.0,<3.0.0)
Requires-Dist: pyyaml (>=6.0.2,<7.0.0)
Requires-Dist: requests (>=2.31.0,<2.32.0)
Requires-Dist: requests-oauthlib (>=2.0.0,<3.0.0)
Project-URL: Repository, https://github.com/ishahroz/superset-python-client
